{
  "generated_by": "socotra-jar-building-block/scripts/build_catalog.py",
  "customer_jar": "customer-config.jar",
  "datamodel_jar": "core-datamodel-v1.7.61.jar",
  "datamodel_version": "1.7.61",
  "products": [
    "ZenCover"
  ],
  "depth": 3,
  "roots": {
    "ZenCoverQuote": {
      "fqcn": "com.socotra.deployment.customer.ZenCoverQuote",
      "paths": {
        "accountLocator": "com.socotra.platform.tools.ULID",
        "anonymizeData": "com.socotra.deployment.customer.ZenCoverQuote",
        "autoRenewalPlanName": "java.util.Optional<java.lang.String>",
        "billingLevel": "com.socotra.coremodel.BillingLevel",
        "contactSlots": "java.util.Map<java.lang.String, com.socotra.coremodel.ContactSlot>",
        "contacts": "java.util.Collection<com.socotra.coremodel.ContactRoles>",
        "createdAt": "java.util.Optional<java.time.Instant>",
        "createdBy": "java.util.Optional<java.util.UUID>",
        "currency": "java.util.Optional<java.lang.String>",
        "data": "com.socotra.deployment.customer.ZenCoverQuote$ZenCoverQuoteData",
        "delinquencyPlanName": "java.util.Optional<java.lang.String>",
        "durationBasis": "java.util.Optional<com.socotra.coremodel.DurationBasis>",
        "element": "com.socotra.coremodel.Element",
        "endTime": "java.util.Optional<java.time.Instant>",
        "expirationTime": "java.util.Optional<java.time.Instant>",
        "groupLocator": "com.socotra.platform.tools.ULID",
        "invoiceFeeAmount": "java.util.Optional<java.math.BigDecimal>",
        "items": "java.util.Collection<com.socotra.deployment.customer.ItemQuote>",
        "jurisdiction": "java.util.Optional<java.lang.String>",
        "locator": "com.socotra.platform.tools.ULID",
        "numberingTrigger": "com.socotra.coremodel.NumberingTrigger",
        "policyLocator": "java.util.Optional<com.socotra.platform.tools.ULID>",
        "preferences": "java.util.Optional<com.socotra.coremodel.Preferences>",
        "producerCode": "java.util.Optional<java.lang.String>",
        "productName": "java.lang.String",
        "quoteNumber": "java.util.Optional<java.lang.String>",
        "quoteState": "com.socotra.coremodel.QuoteState",
        "region": "java.util.Optional<java.lang.String>",
        "reservedPolicyNumber": "java.util.Optional<java.lang.String>",
        "startTime": "java.util.Optional<java.time.Instant>",
        "timezone": "java.util.Optional<java.lang.String>",
        "type": "java.lang.String",
        "underwritingStatus": "java.util.Optional<java.lang.String>",
        "accountLocator.generate": "com.socotra.platform.tools.ULID",
        "accountLocator.getLeastSignificantBits": "long",
        "accountLocator.getMostSignificantBits": "long",
        "accountLocator.getTime": "long",
        "accountLocator.increment": "com.socotra.platform.tools.ULID",
        "accountLocator.toLowerString": "java.lang.String",
        "billingLevel.values": "com.socotra.coremodel.BillingLevel[]",
        "contacts.contactLocator": "com.socotra.platform.tools.ULID",
        "contacts.roles": "java.util.Collection<java.lang.String>",
        "data.anonymizeData": "com.socotra.deployment.customer.ZenCoverQuote$ZenCoverQuoteData",
        "data.contractTermEndDate": "java.time.OffsetDateTime",
        "data.coolingOffPeriod": "java.lang.Integer",
        "data.discountAmount": "java.math.BigDecimal",
        "data.discountProfileCode": "java.lang.String",
        "data.discountTerm": "java.lang.String",
        "data.discountType": "java.lang.String",
        "data.expectedRenewalDate": "java.time.LocalDate",
        "data.gracePeriod": "java.lang.Integer",
        "data.gracePeriodType": "java.lang.String",
        "data.newBusinessWaitPeriod": "java.lang.Integer",
        "data.settlementPeriod": "java.lang.Integer",
        "data.settlementPeriodOffsetInDays": "java.lang.Integer",
        "data.settlementPeriodType": "java.lang.String",
        "data.type": "java.lang.String",
        "durationBasis.toInt": "int",
        "durationBasis.values": "com.socotra.coremodel.DurationBasis[]",
        "element.category": "java.util.Optional<com.socotra.coremodel.ElementCategory>",
        "element.coverageTerms": "java.util.Map<java.lang.String, java.lang.Object>",
        "element.data": "java.util.Map<java.lang.String, java.lang.Object>",
        "element.elements": "java.util.Collection<com.socotra.coremodel.Element>",
        "element.locator": "com.socotra.platform.tools.ULID",
        "element.originalEffectiveTime": "java.util.Optional<java.time.Instant>",
        "element.parentLocator": "com.socotra.platform.tools.ULID",
        "element.rootLocator": "com.socotra.platform.tools.ULID",
        "element.staticLocator": "com.socotra.platform.tools.ULID",
        "element.tenantLocator": "java.util.UUID",
        "element.type": "java.lang.String",
        "groupLocator.generate": "com.socotra.platform.tools.ULID",
        "groupLocator.getLeastSignificantBits": "long",
        "groupLocator.getMostSignificantBits": "long",
        "groupLocator.getTime": "long",
        "groupLocator.increment": "com.socotra.platform.tools.ULID",
        "groupLocator.toLowerString": "java.lang.String",
        "items.accidentalDamage": "com.socotra.deployment.customer.AccidentalDamageQuote",
        "items.anonymizeData": "com.socotra.deployment.customer.ItemQuote",
        "items.breakdown": "com.socotra.deployment.customer.BreakdownQuote",
        "items.data": "com.socotra.deployment.customer.ItemQuote$ItemQuoteData",
        "items.element": "com.socotra.coremodel.Element",
        "items.locator": "com.socotra.platform.tools.ULID",
        "items.theft": "com.socotra.deployment.customer.TheftQuote",
        "items.type": "java.lang.String",
        "locator.generate": "com.socotra.platform.tools.ULID",
        "locator.getLeastSignificantBits": "long",
        "locator.getMostSignificantBits": "long",
        "locator.getTime": "long",
        "locator.increment": "com.socotra.platform.tools.ULID",
        "locator.toLowerString": "java.lang.String",
        "numberingTrigger.values": "com.socotra.coremodel.NumberingTrigger[]",
        "policyLocator.generate": "com.socotra.platform.tools.ULID",
        "policyLocator.getLeastSignificantBits": "long",
        "policyLocator.getMostSignificantBits": "long",
        "policyLocator.getTime": "long",
        "policyLocator.increment": "com.socotra.platform.tools.ULID",
        "policyLocator.toLowerString": "java.lang.String",
        "preferences.installmentPreferences": "java.util.Optional<com.socotra.coremodel.InstallmentPreferences>",
        "quoteState.values": "com.socotra.coremodel.QuoteState[]",
        "contacts.contactLocator.generate": "com.socotra.platform.tools.ULID",
        "contacts.contactLocator.getLeastSignificantBits": "long",
        "contacts.contactLocator.getMostSignificantBits": "long",
        "contacts.contactLocator.getTime": "long",
        "contacts.contactLocator.increment": "com.socotra.platform.tools.ULID",
        "contacts.contactLocator.toLowerString": "java.lang.String",
        "element.category.values": "com.socotra.coremodel.ElementCategory[]",
        "element.locator.generate": "com.socotra.platform.tools.ULID",
        "element.locator.getLeastSignificantBits": "long",
        "element.locator.getMostSignificantBits": "long",
        "element.locator.getTime": "long",
        "element.locator.increment": "com.socotra.platform.tools.ULID",
        "element.locator.toLowerString": "java.lang.String",
        "element.parentLocator.generate": "com.socotra.platform.tools.ULID",
        "element.parentLocator.getLeastSignificantBits": "long",
        "element.parentLocator.getMostSignificantBits": "long",
        "element.parentLocator.getTime": "long",
        "element.parentLocator.increment": "com.socotra.platform.tools.ULID",
        "element.parentLocator.toLowerString": "java.lang.String",
        "element.rootLocator.generate": "com.socotra.platform.tools.ULID",
        "element.rootLocator.getLeastSignificantBits": "long",
        "element.rootLocator.getMostSignificantBits": "long",
        "element.rootLocator.getTime": "long",
        "element.rootLocator.increment": "com.socotra.platform.tools.ULID",
        "element.rootLocator.toLowerString": "java.lang.String",
        "element.staticLocator.generate": "com.socotra.platform.tools.ULID",
        "element.staticLocator.getLeastSignificantBits": "long",
        "element.staticLocator.getMostSignificantBits": "long",
        "element.staticLocator.getTime": "long",
        "element.staticLocator.increment": "com.socotra.platform.tools.ULID",
        "element.staticLocator.toLowerString": "java.lang.String",
        "items.accidentalDamage.anonymizeData": "com.socotra.deployment.customer.AccidentalDamageQuote",
        "items.accidentalDamage.data": "com.socotra.deployment.customer.AccidentalDamageQuote$AccidentalDamageQuoteData",
        "items.accidentalDamage.element": "com.socotra.coremodel.Element",
        "items.accidentalDamage.locator": "com.socotra.platform.tools.ULID",
        "items.accidentalDamage.type": "java.lang.String",
        "items.accidentalDamage.zeroDeductible": "com.socotra.deployment.customer.ZeroDeductible",
        "items.breakdown.anonymizeData": "com.socotra.deployment.customer.BreakdownQuote",
        "items.breakdown.data": "com.socotra.deployment.customer.BreakdownQuote$BreakdownQuoteData",
        "items.breakdown.element": "com.socotra.coremodel.Element",
        "items.breakdown.locator": "com.socotra.platform.tools.ULID",
        "items.breakdown.type": "java.lang.String",
        "items.breakdown.zeroDeductible": "com.socotra.deployment.customer.ZeroDeductible",
        "items.data.anonymizeData": "com.socotra.deployment.customer.ItemQuote$ItemQuoteData",
        "items.data.itemInWarrantyAtTakeup": "java.lang.Boolean",
        "items.data.itemInWorkingOrderAtTakeup": "java.lang.Boolean",
        "items.data.itemTypeCode": "java.lang.String",
        "items.data.manufacturerLabourGuaranteePeriod": "java.lang.Integer",
        "items.data.purchaseDate": "java.time.LocalDate",
        "items.data.purchasePrice": "java.math.BigDecimal",
        "items.data.serialNumber": "java.lang.Integer",
        "items.data.type": "java.lang.String",
        "items.element.category": "java.util.Optional<com.socotra.coremodel.ElementCategory>",
        "items.element.coverageTerms": "java.util.Map<java.lang.String, java.lang.Object>",
        "items.element.data": "java.util.Map<java.lang.String, java.lang.Object>",
        "items.element.elements": "java.util.Collection<com.socotra.coremodel.Element>",
        "items.element.locator": "com.socotra.platform.tools.ULID",
        "items.element.originalEffectiveTime": "java.util.Optional<java.time.Instant>",
        "items.element.parentLocator": "com.socotra.platform.tools.ULID",
        "items.element.rootLocator": "com.socotra.platform.tools.ULID",
        "items.element.staticLocator": "com.socotra.platform.tools.ULID",
        "items.element.tenantLocator": "java.util.UUID",
        "items.element.type": "java.lang.String",
        "items.locator.generate": "com.socotra.platform.tools.ULID",
        "items.locator.getLeastSignificantBits": "long",
        "items.locator.getMostSignificantBits": "long",
        "items.locator.getTime": "long",
        "items.locator.increment": "com.socotra.platform.tools.ULID",
        "items.locator.toLowerString": "java.lang.String",
        "items.theft.anonymizeData": "com.socotra.deployment.customer.TheftQuote",
        "items.theft.element": "com.socotra.coremodel.Element",
        "items.theft.locator": "com.socotra.platform.tools.ULID",
        "items.theft.type": "java.lang.String",
        "preferences.installmentPreferences.anchorMode": "java.util.Optional<com.socotra.coremodel.InstallmentAnchorMode>",
        "preferences.installmentPreferences.anchorTime": "java.util.Optional<java.time.Instant>",
        "preferences.installmentPreferences.anchorType": "java.util.Optional<com.socotra.coremodel.InstallmentAnchorType>",
        "preferences.installmentPreferences.autopayLeadDays": "java.util.Optional<java.math.BigDecimal>",
        "preferences.installmentPreferences.cadence": "java.util.Optional<com.socotra.coremodel.InstallmentCadence>",
        "preferences.installmentPreferences.dayOfMonth": "java.util.Optional<java.lang.Integer>",
        "preferences.installmentPreferences.dayOfWeek": "java.util.Optional<com.socotra.coremodel.DayOfWeek>",
        "preferences.installmentPreferences.dueLeadDays": "java.util.Optional<java.lang.Integer>",
        "preferences.installmentPreferences.generateLeadDays": "java.util.Optional<java.lang.Integer>",
        "preferences.installmentPreferences.installmentPlanName": "java.util.Optional<java.lang.String>",
        "preferences.installmentPreferences.installmentWeights": "java.util.Collection<java.math.BigDecimal>",
        "preferences.installmentPreferences.maxInstallmentsPerTerm": "java.util.Optional<java.lang.Integer>",
        "preferences.installmentPreferences.weekOfMonth": "java.util.Optional<com.socotra.coremodel.WeekOfMonth>"
      }
    },
    "ZenCoverSegment": {
      "fqcn": "com.socotra.deployment.customer.ZenCoverSegment",
      "paths": {
        "anonymizeData": "com.socotra.deployment.customer.ZenCoverSegment",
        "basedOn": "java.util.Optional<com.socotra.platform.tools.ULID>",
        "data": "com.socotra.deployment.customer.ZenCoverSegment$ZenCoverSegmentData",
        "duration": "java.math.BigDecimal",
        "element": "com.socotra.coremodel.Element",
        "endTime": "java.time.Instant",
        "items": "java.util.Collection<com.socotra.deployment.customer.ItemPolicy>",
        "locator": "com.socotra.platform.tools.ULID",
        "originalEffectiveTime": "java.time.Instant",
        "producerInfo": "java.util.Optional<com.socotra.coremodel.ProducerInfo>",
        "segmentType": "com.socotra.coremodel.SegmentType",
        "startTime": "java.time.Instant",
        "transactionLocator": "com.socotra.platform.tools.ULID",
        "type": "java.lang.String",
        "basedOn.generate": "com.socotra.platform.tools.ULID",
        "basedOn.getLeastSignificantBits": "long",
        "basedOn.getMostSignificantBits": "long",
        "basedOn.getTime": "long",
        "basedOn.increment": "com.socotra.platform.tools.ULID",
        "basedOn.toLowerString": "java.lang.String",
        "data.anonymizeData": "com.socotra.deployment.customer.ZenCoverSegment$ZenCoverSegmentData",
        "data.contractTermEndDate": "java.time.OffsetDateTime",
        "data.coolingOffPeriod": "java.lang.Integer",
        "data.discountAmount": "java.math.BigDecimal",
        "data.discountProfileCode": "java.lang.String",
        "data.discountTerm": "java.lang.String",
        "data.discountType": "java.lang.String",
        "data.expectedRenewalDate": "java.time.LocalDate",
        "data.gracePeriod": "java.lang.Integer",
        "data.gracePeriodType": "java.lang.String",
        "data.newBusinessWaitPeriod": "java.lang.Integer",
        "data.settlementPeriod": "java.lang.Integer",
        "data.settlementPeriodOffsetInDays": "java.lang.Integer",
        "data.settlementPeriodType": "java.lang.String",
        "data.type": "java.lang.String",
        "element.category": "java.util.Optional<com.socotra.coremodel.ElementCategory>",
        "element.coverageTerms": "java.util.Map<java.lang.String, java.lang.Object>",
        "element.data": "java.util.Map<java.lang.String, java.lang.Object>",
        "element.elements": "java.util.Collection<com.socotra.coremodel.Element>",
        "element.locator": "com.socotra.platform.tools.ULID",
        "element.originalEffectiveTime": "java.util.Optional<java.time.Instant>",
        "element.parentLocator": "com.socotra.platform.tools.ULID",
        "element.rootLocator": "com.socotra.platform.tools.ULID",
        "element.staticLocator": "com.socotra.platform.tools.ULID",
        "element.tenantLocator": "java.util.UUID",
        "element.type": "java.lang.String",
        "items.accidentalDamage": "com.socotra.deployment.customer.AccidentalDamagePolicy",
        "items.anonymizeData": "com.socotra.deployment.customer.ItemPolicy",
        "items.breakdown": "com.socotra.deployment.customer.BreakdownPolicy",
        "items.data": "com.socotra.deployment.customer.ItemPolicy$ItemPolicyData",
        "items.element": "com.socotra.coremodel.Element",
        "items.locator": "com.socotra.platform.tools.ULID",
        "items.originalEffectiveTime": "java.time.Instant",
        "items.theft": "com.socotra.deployment.customer.TheftPolicy",
        "items.type": "java.lang.String",
        "locator.generate": "com.socotra.platform.tools.ULID",
        "locator.getLeastSignificantBits": "long",
        "locator.getMostSignificantBits": "long",
        "locator.getTime": "long",
        "locator.increment": "com.socotra.platform.tools.ULID",
        "locator.toLowerString": "java.lang.String",
        "producerInfo.producerCode": "java.util.Optional<java.lang.String>",
        "producerInfo.producerCodeOfRecord": "java.util.Optional<java.lang.String>",
        "segmentType.values": "com.socotra.coremodel.SegmentType[]",
        "transactionLocator.generate": "com.socotra.platform.tools.ULID",
        "transactionLocator.getLeastSignificantBits": "long",
        "transactionLocator.getMostSignificantBits": "long",
        "transactionLocator.getTime": "long",
        "transactionLocator.increment": "com.socotra.platform.tools.ULID",
        "transactionLocator.toLowerString": "java.lang.String",
        "element.category.values": "com.socotra.coremodel.ElementCategory[]",
        "element.locator.generate": "com.socotra.platform.tools.ULID",
        "element.locator.getLeastSignificantBits": "long",
        "element.locator.getMostSignificantBits": "long",
        "element.locator.getTime": "long",
        "element.locator.increment": "com.socotra.platform.tools.ULID",
        "element.locator.toLowerString": "java.lang.String",
        "element.parentLocator.generate": "com.socotra.platform.tools.ULID",
        "element.parentLocator.getLeastSignificantBits": "long",
        "element.parentLocator.getMostSignificantBits": "long",
        "element.parentLocator.getTime": "long",
        "element.parentLocator.increment": "com.socotra.platform.tools.ULID",
        "element.parentLocator.toLowerString": "java.lang.String",
        "element.rootLocator.generate": "com.socotra.platform.tools.ULID",
        "element.rootLocator.getLeastSignificantBits": "long",
        "element.rootLocator.getMostSignificantBits": "long",
        "element.rootLocator.getTime": "long",
        "element.rootLocator.increment": "com.socotra.platform.tools.ULID",
        "element.rootLocator.toLowerString": "java.lang.String",
        "element.staticLocator.generate": "com.socotra.platform.tools.ULID",
        "element.staticLocator.getLeastSignificantBits": "long",
        "element.staticLocator.getMostSignificantBits": "long",
        "element.staticLocator.getTime": "long",
        "element.staticLocator.increment": "com.socotra.platform.tools.ULID",
        "element.staticLocator.toLowerString": "java.lang.String",
        "items.accidentalDamage.anonymizeData": "com.socotra.deployment.customer.AccidentalDamagePolicy",
        "items.accidentalDamage.data": "com.socotra.deployment.customer.AccidentalDamagePolicy$AccidentalDamagePolicyData",
        "items.accidentalDamage.element": "com.socotra.coremodel.Element",
        "items.accidentalDamage.locator": "com.socotra.platform.tools.ULID",
        "items.accidentalDamage.originalEffectiveTime": "java.time.Instant",
        "items.accidentalDamage.type": "java.lang.String",
        "items.accidentalDamage.zeroDeductible": "com.socotra.deployment.customer.ZeroDeductible",
        "items.breakdown.anonymizeData": "com.socotra.deployment.customer.BreakdownPolicy",
        "items.breakdown.data": "com.socotra.deployment.customer.BreakdownPolicy$BreakdownPolicyData",
        "items.breakdown.element": "com.socotra.coremodel.Element",
        "items.breakdown.locator": "com.socotra.platform.tools.ULID",
        "items.breakdown.originalEffectiveTime": "java.time.Instant",
        "items.breakdown.type": "java.lang.String",
        "items.breakdown.zeroDeductible": "com.socotra.deployment.customer.ZeroDeductible",
        "items.data.anonymizeData": "com.socotra.deployment.customer.ItemPolicy$ItemPolicyData",
        "items.data.itemInWarrantyAtTakeup": "java.lang.Boolean",
        "items.data.itemInWorkingOrderAtTakeup": "java.lang.Boolean",
        "items.data.itemTypeCode": "java.lang.String",
        "items.data.manufacturerLabourGuaranteePeriod": "java.lang.Integer",
        "items.data.purchaseDate": "java.time.LocalDate",
        "items.data.purchasePrice": "java.math.BigDecimal",
        "items.data.serialNumber": "java.lang.Integer",
        "items.data.type": "java.lang.String",
        "items.element.category": "java.util.Optional<com.socotra.coremodel.ElementCategory>",
        "items.element.coverageTerms": "java.util.Map<java.lang.String, java.lang.Object>",
        "items.element.data": "java.util.Map<java.lang.String, java.lang.Object>",
        "items.element.elements": "java.util.Collection<com.socotra.coremodel.Element>",
        "items.element.locator": "com.socotra.platform.tools.ULID",
        "items.element.originalEffectiveTime": "java.util.Optional<java.time.Instant>",
        "items.element.parentLocator": "com.socotra.platform.tools.ULID",
        "items.element.rootLocator": "com.socotra.platform.tools.ULID",
        "items.element.staticLocator": "com.socotra.platform.tools.ULID",
        "items.element.tenantLocator": "java.util.UUID",
        "items.element.type": "java.lang.String",
        "items.locator.generate": "com.socotra.platform.tools.ULID",
        "items.locator.getLeastSignificantBits": "long",
        "items.locator.getMostSignificantBits": "long",
        "items.locator.getTime": "long",
        "items.locator.increment": "com.socotra.platform.tools.ULID",
        "items.locator.toLowerString": "java.lang.String",
        "items.theft.anonymizeData": "com.socotra.deployment.customer.TheftPolicy",
        "items.theft.element": "com.socotra.coremodel.Element",
        "items.theft.locator": "com.socotra.platform.tools.ULID",
        "items.theft.originalEffectiveTime": "java.time.Instant",
        "items.theft.type": "java.lang.String"
      }
    },
    "ZenCoverQuickQuote": {
      "fqcn": "com.socotra.deployment.customer.ZenCoverQuickQuote",
      "paths": {
        "accountLocator": "java.util.Optional<com.socotra.platform.tools.ULID>",
        "anonymizeData": "com.socotra.deployment.customer.ZenCoverQuickQuote",
        "contactSlots": "java.util.Map<java.lang.String, com.socotra.coremodel.ContactSlot>",
        "contacts": "java.util.Collection<com.socotra.coremodel.ContactRoles>",
        "createdAt": "java.util.Optional<java.time.Instant>",
        "createdBy": "java.util.Optional<java.util.UUID>",
        "currency": "java.util.Optional<java.lang.String>",
        "data": "com.socotra.deployment.customer.ZenCoverQuickQuote$ZenCoverQuickQuoteData",
        "durationBasis": "java.util.Optional<com.socotra.coremodel.DurationBasis>",
        "element": "com.socotra.coremodel.Element",
        "endTime": "java.util.Optional<java.time.Instant>",
        "expirationTime": "java.util.Optional<java.time.Instant>",
        "items": "java.util.Collection<com.socotra.deployment.customer.ItemQuickQuote>",
        "jurisdiction": "java.util.Optional<java.lang.String>",
        "locator": "com.socotra.platform.tools.ULID",
        "productName": "java.lang.String",
        "quickQuoteState": "com.socotra.coremodel.QuickQuoteState",
        "startTime": "java.util.Optional<java.time.Instant>",
        "timezone": "java.util.Optional<java.lang.String>",
        "type": "java.lang.String",
        "accountLocator.generate": "com.socotra.platform.tools.ULID",
        "accountLocator.getLeastSignificantBits": "long",
        "accountLocator.getMostSignificantBits": "long",
        "accountLocator.getTime": "long",
        "accountLocator.increment": "com.socotra.platform.tools.ULID",
        "accountLocator.toLowerString": "java.lang.String",
        "contacts.contactLocator": "com.socotra.platform.tools.ULID",
        "contacts.roles": "java.util.Collection<java.lang.String>",
        "data.anonymizeData": "com.socotra.deployment.customer.ZenCoverQuickQuote$ZenCoverQuickQuoteData",
        "data.contractTermEndDate": "java.time.OffsetDateTime",
        "data.coolingOffPeriod": "java.lang.Integer",
        "data.discountAmount": "java.math.BigDecimal",
        "data.discountProfileCode": "java.lang.String",
        "data.discountTerm": "java.lang.String",
        "data.discountType": "java.lang.String",
        "data.expectedRenewalDate": "java.time.LocalDate",
        "data.gracePeriod": "java.lang.Integer",
        "data.gracePeriodType": "java.lang.String",
        "data.newBusinessWaitPeriod": "java.lang.Integer",
        "data.settlementPeriod": "java.lang.Integer",
        "data.settlementPeriodOffsetInDays": "java.lang.Integer",
        "data.settlementPeriodType": "java.lang.String",
        "data.type": "java.lang.String",
        "durationBasis.toInt": "int",
        "durationBasis.values": "com.socotra.coremodel.DurationBasis[]",
        "element.category": "java.util.Optional<com.socotra.coremodel.ElementCategory>",
        "element.coverageTerms": "java.util.Map<java.lang.String, java.lang.Object>",
        "element.data": "java.util.Map<java.lang.String, java.lang.Object>",
        "element.elements": "java.util.Collection<com.socotra.coremodel.Element>",
        "element.locator": "com.socotra.platform.tools.ULID",
        "element.originalEffectiveTime": "java.util.Optional<java.time.Instant>",
        "element.parentLocator": "com.socotra.platform.tools.ULID",
        "element.rootLocator": "com.socotra.platform.tools.ULID",
        "element.staticLocator": "com.socotra.platform.tools.ULID",
        "element.tenantLocator": "java.util.UUID",
        "element.type": "java.lang.String",
        "items.accidentalDamage": "com.socotra.deployment.customer.AccidentalDamageQuickQuote",
        "items.anonymizeData": "com.socotra.deployment.customer.ItemQuickQuote",
        "items.breakdown": "com.socotra.deployment.customer.BreakdownQuickQuote",
        "items.data": "com.socotra.deployment.customer.ItemQuickQuote$ItemQuickQuoteData",
        "items.element": "com.socotra.coremodel.Element",
        "items.locator": "com.socotra.platform.tools.ULID",
        "items.theft": "com.socotra.deployment.customer.TheftQuickQuote",
        "items.type": "java.lang.String",
        "locator.generate": "com.socotra.platform.tools.ULID",
        "locator.getLeastSignificantBits": "long",
        "locator.getMostSignificantBits": "long",
        "locator.getTime": "long",
        "locator.increment": "com.socotra.platform.tools.ULID",
        "locator.toLowerString": "java.lang.String",
        "quickQuoteState.values": "com.socotra.coremodel.QuickQuoteState[]",
        "contacts.contactLocator.generate": "com.socotra.platform.tools.ULID",
        "contacts.contactLocator.getLeastSignificantBits": "long",
        "contacts.contactLocator.getMostSignificantBits": "long",
        "contacts.contactLocator.getTime": "long",
        "contacts.contactLocator.increment": "com.socotra.platform.tools.ULID",
        "contacts.contactLocator.toLowerString": "java.lang.String",
        "element.category.values": "com.socotra.coremodel.ElementCategory[]",
        "element.locator.generate": "com.socotra.platform.tools.ULID",
        "element.locator.getLeastSignificantBits": "long",
        "element.locator.getMostSignificantBits": "long",
        "element.locator.getTime": "long",
        "element.locator.increment": "com.socotra.platform.tools.ULID",
        "element.locator.toLowerString": "java.lang.String",
        "element.parentLocator.generate": "com.socotra.platform.tools.ULID",
        "element.parentLocator.getLeastSignificantBits": "long",
        "element.parentLocator.getMostSignificantBits": "long",
        "element.parentLocator.getTime": "long",
        "element.parentLocator.increment": "com.socotra.platform.tools.ULID",
        "element.parentLocator.toLowerString": "java.lang.String",
        "element.rootLocator.generate": "com.socotra.platform.tools.ULID",
        "element.rootLocator.getLeastSignificantBits": "long",
        "element.rootLocator.getMostSignificantBits": "long",
        "element.rootLocator.getTime": "long",
        "element.rootLocator.increment": "com.socotra.platform.tools.ULID",
        "element.rootLocator.toLowerString": "java.lang.String",
        "element.staticLocator.generate": "com.socotra.platform.tools.ULID",
        "element.staticLocator.getLeastSignificantBits": "long",
        "element.staticLocator.getMostSignificantBits": "long",
        "element.staticLocator.getTime": "long",
        "element.staticLocator.increment": "com.socotra.platform.tools.ULID",
        "element.staticLocator.toLowerString": "java.lang.String",
        "items.accidentalDamage.anonymizeData": "com.socotra.deployment.customer.AccidentalDamageQuickQuote",
        "items.accidentalDamage.data": "com.socotra.deployment.customer.AccidentalDamageQuickQuote$AccidentalDamageQuickQuoteData",
        "items.accidentalDamage.element": "com.socotra.coremodel.Element",
        "items.accidentalDamage.locator": "com.socotra.platform.tools.ULID",
        "items.accidentalDamage.type": "java.lang.String",
        "items.accidentalDamage.zeroDeductible": "com.socotra.deployment.customer.ZeroDeductible",
        "items.breakdown.anonymizeData": "com.socotra.deployment.customer.BreakdownQuickQuote",
        "items.breakdown.data": "com.socotra.deployment.customer.BreakdownQuickQuote$BreakdownQuickQuoteData",
        "items.breakdown.element": "com.socotra.coremodel.Element",
        "items.breakdown.locator": "com.socotra.platform.tools.ULID",
        "items.breakdown.type": "java.lang.String",
        "items.breakdown.zeroDeductible": "com.socotra.deployment.customer.ZeroDeductible",
        "items.data.anonymizeData": "com.socotra.deployment.customer.ItemQuickQuote$ItemQuickQuoteData",
        "items.data.itemInWarrantyAtTakeup": "java.lang.Boolean",
        "items.data.itemInWorkingOrderAtTakeup": "java.lang.Boolean",
        "items.data.itemTypeCode": "java.lang.String",
        "items.data.manufacturerLabourGuaranteePeriod": "java.lang.Integer",
        "items.data.purchaseDate": "java.time.LocalDate",
        "items.data.purchasePrice": "java.math.BigDecimal",
        "items.data.serialNumber": "java.lang.Integer",
        "items.data.type": "java.lang.String",
        "items.element.category": "java.util.Optional<com.socotra.coremodel.ElementCategory>",
        "items.element.coverageTerms": "java.util.Map<java.lang.String, java.lang.Object>",
        "items.element.data": "java.util.Map<java.lang.String, java.lang.Object>",
        "items.element.elements": "java.util.Collection<com.socotra.coremodel.Element>",
        "items.element.locator": "com.socotra.platform.tools.ULID",
        "items.element.originalEffectiveTime": "java.util.Optional<java.time.Instant>",
        "items.element.parentLocator": "com.socotra.platform.tools.ULID",
        "items.element.rootLocator": "com.socotra.platform.tools.ULID",
        "items.element.staticLocator": "com.socotra.platform.tools.ULID",
        "items.element.tenantLocator": "java.util.UUID",
        "items.element.type": "java.lang.String",
        "items.locator.generate": "com.socotra.platform.tools.ULID",
        "items.locator.getLeastSignificantBits": "long",
        "items.locator.getMostSignificantBits": "long",
        "items.locator.getTime": "long",
        "items.locator.increment": "com.socotra.platform.tools.ULID",
        "items.locator.toLowerString": "java.lang.String",
        "items.theft.anonymizeData": "com.socotra.deployment.customer.TheftQuickQuote",
        "items.theft.element": "com.socotra.coremodel.Element",
        "items.theft.locator": "com.socotra.platform.tools.ULID",
        "items.theft.type": "java.lang.String"
      }
    },
    "PersonalAccount": {
      "fqcn": "com.socotra.deployment.customer.PersonalAccount",
      "paths": {
        "accountNumber": "java.util.Optional<java.lang.String>",
        "anonymizeData": "com.socotra.deployment.customer.PersonalAccount",
        "autoRenewalPlanName": "java.util.Optional<java.lang.String>",
        "billingLevel": "com.socotra.coremodel.BillingLevel",
        "contactSlots": "java.util.Map<java.lang.String, com.socotra.coremodel.ContactSlot>",
        "contacts": "java.util.Collection<com.socotra.coremodel.ContactRoles>",
        "data": "com.socotra.deployment.customer.PersonalAccount$PersonalAccountData",
        "delinquencyPlanName": "java.util.Optional<java.lang.String>",
        "excessCreditPlanName": "java.util.Optional<java.lang.String>",
        "invoiceDocument": "java.util.Optional<java.lang.String>",
        "locator": "com.socotra.platform.tools.ULID",
        "numberingTrigger": "com.socotra.coremodel.NumberingTrigger",
        "paymentExecutionRetryPlanName": "java.util.Optional<java.lang.String>",
        "preferences": "java.util.Optional<com.socotra.coremodel.Preferences>",
        "region": "java.util.Optional<java.lang.String>",
        "shortfallTolerancePlanName": "java.util.Optional<java.lang.String>",
        "type": "java.lang.String",
        "billingLevel.values": "com.socotra.coremodel.BillingLevel[]",
        "contacts.contactLocator": "com.socotra.platform.tools.ULID",
        "contacts.roles": "java.util.Collection<java.lang.String>",
        "data.anonymizeData": "com.socotra.deployment.customer.PersonalAccount$PersonalAccountData",
        "data.email": "java.lang.String",
        "data.firstName": "java.lang.String",
        "data.lastName": "java.lang.String",
        "data.primaryPhone": "java.lang.String",
        "data.type": "java.lang.String",
        "locator.generate": "com.socotra.platform.tools.ULID",
        "locator.getLeastSignificantBits": "long",
        "locator.getMostSignificantBits": "long",
        "locator.getTime": "long",
        "locator.increment": "com.socotra.platform.tools.ULID",
        "locator.toLowerString": "java.lang.String",
        "numberingTrigger.values": "com.socotra.coremodel.NumberingTrigger[]",
        "preferences.installmentPreferences": "java.util.Optional<com.socotra.coremodel.InstallmentPreferences>",
        "contacts.contactLocator.generate": "com.socotra.platform.tools.ULID",
        "contacts.contactLocator.getLeastSignificantBits": "long",
        "contacts.contactLocator.getMostSignificantBits": "long",
        "contacts.contactLocator.getTime": "long",
        "contacts.contactLocator.increment": "com.socotra.platform.tools.ULID",
        "contacts.contactLocator.toLowerString": "java.lang.String",
        "preferences.installmentPreferences.anchorMode": "java.util.Optional<com.socotra.coremodel.InstallmentAnchorMode>",
        "preferences.installmentPreferences.anchorTime": "java.util.Optional<java.time.Instant>",
        "preferences.installmentPreferences.anchorType": "java.util.Optional<com.socotra.coremodel.InstallmentAnchorType>",
        "preferences.installmentPreferences.autopayLeadDays": "java.util.Optional<java.math.BigDecimal>",
        "preferences.installmentPreferences.cadence": "java.util.Optional<com.socotra.coremodel.InstallmentCadence>",
        "preferences.installmentPreferences.dayOfMonth": "java.util.Optional<java.lang.Integer>",
        "preferences.installmentPreferences.dayOfWeek": "java.util.Optional<com.socotra.coremodel.DayOfWeek>",
        "preferences.installmentPreferences.dueLeadDays": "java.util.Optional<java.lang.Integer>",
        "preferences.installmentPreferences.generateLeadDays": "java.util.Optional<java.lang.Integer>",
        "preferences.installmentPreferences.installmentPlanName": "java.util.Optional<java.lang.String>",
        "preferences.installmentPreferences.installmentWeights": "java.util.Collection<java.math.BigDecimal>",
        "preferences.installmentPreferences.maxInstallmentsPerTerm": "java.util.Optional<java.lang.Integer>",
        "preferences.installmentPreferences.weekOfMonth": "java.util.Optional<com.socotra.coremodel.WeekOfMonth>"
      }
    }
  }
}
